setup.py
nefertari_sqla/__init__.py
nefertari_sqla/documents.py
nefertari_sqla/fields.py
nefertari_sqla/serializers.py
nefertari_sqla/signals.py
nefertari_sqla/types.py
nefertari_sqla/utils.py
nefertari_sqla.egg-info/PKG-INFO
nefertari_sqla.egg-info/SOURCES.txt
nefertari_sqla.egg-info/dependency_links.txt
nefertari_sqla.egg-info/not-zip-safe
nefertari_sqla.egg-info/pbr.json
nefertari_sqla.egg-info/requires.txt
nefertari_sqla.egg-info/top_level.txt
nefertari_sqla/tests/__init__.py
nefertari_sqla/tests/fixtures.py
nefertari_sqla/tests/test_documents.py
nefertari_sqla/tests/test_types.py