Metadata-Version: 1.1
Name: nefertari-sqla
Version: 0.4.2
Summary: sqla engine for nefertari
Home-page: https://github.com/ramses-tech/nefertari-sqla
Author: Ramses
Author-email: hello@ramses.tech
License: UNKNOWN
Keywords: web wsgi bfg pylons pyramid rest sqlalchemy
Platform: UNKNOWN
Classifier: Programming Language :: Python
Classifier: Programming Language :: Python :: 2
Classifier: Programming Language :: Python :: 2.7
Classifier: Programming Language :: Python :: 3
Classifier: Programming Language :: Python :: 3.4
Classifier: Programming Language :: Python :: 3.5
Classifier: Framework :: Pyramid
Classifier: Topic :: Internet :: WWW/HTTP
Classifier: Topic :: Internet :: WWW/HTTP :: WSGI :: Application
Classifier: Topic :: Database
Classifier: Topic :: Database :: Database Engines/Servers
